{
    "inference_id": "e131dbc8-de3b-4af8-a6d7-ac131981e9ec",
    "time": 0.07327329400050075,
    "image": {
        "width": 592,
        "height": 418
    },
    "predictions": [
        {
            "x": 49.0,
            "y": 284.0,
            "width": 38.0,
            "height": 26.0,
            "confidence": 0.7256406545639038,
            "class": "Tomato leaf late blight",
            "class_id": 4,
            "detection_id": "b044288b-adff-40f1-9d2a-715aa4bc160e"
        },
        {
            "x": 377.0,
            "y": 258.5,
            "width": 54.0,
            "height": 47.0,
            "confidence": 0.6931542158126831,
            "class": "Tomato leaf late blight",
            "class_id": 4,
            "detection_id": "b9e16c40-cf26-47b2-936c-b5c7bd209b88"
        },
        {
            "x": 285.0,
            "y": 396.0,
            "width": 36.0,
            "height": 40.0,
            "confidence": 0.48738402128219604,
            "class": "Tomato leaf late blight",
            "class_id": 4,
            "detection_id": "e0029ff9-ac48-4f2e-ab0e-e799dce9bb51"
        },
        {
            "x": 387.5,
            "y": 163.5,
            "width": 37.0,
            "height": 37.0,
            "confidence": 0.42107656598091125,
            "class": "Tomato leaf late blight",
            "class_id": 4,
            "detection_id": "f43ceff2-a681-448a-9d67-b86cbb38a48c"
        },
        {
            "x": 387.5,
            "y": 163.5,
            "width": 37.0,
            "height": 37.0,
            "confidence": 0.41992518305778503,
            "class": "Tomato Early blight leaf",
            "class_id": 2,
            "detection_id": "e7d05ada-9321-4c80-acbb-673e7e12315c"
        },
        {
            "x": 369.0,
            "y": 57.5,
            "width": 34.0,
            "height": 45.0,
            "confidence": 0.41672393679618835,
            "class": "Tomato Early blight leaf",
            "class_id": 2,
            "detection_id": "10adf0bb-9251-45b8-b6db-59e86d72fc44"
        },
        {
            "x": 308.0,
            "y": 238.5,
            "width": 46.0,
            "height": 45.0,
            "confidence": 0.41160401701927185,
            "class": "Tomato Early blight leaf",
            "class_id": 2,
            "detection_id": "5edce327-67f9-4bfa-9f40-8486cd18c2b9"
        }
    ]
}